finclaimvalid/__init__.py
finclaimvalid/main.py
finclaimvalid/prompts.py
finclaimvalid-2025.12.21230358.dist-info/METADATA
finclaimvalid-2025.12.21230358.dist-info/WHEEL
finclaimvalid-2025.12.21230358.dist-info/top_level.txt
finclaimvalid-2025.12.21230358.dist-info/RECORD
