Metadata-Version: 2.4
Name: finclaimvalid
Version: 2025.12.21230358
Summary: Verify financial claims with rapid analysis and data-driven insights
Author-email: finclaimvalid <hi@eugene.plus>
License: MIT
Project-URL: Homepage, https://github.com/chigwell/finclaimvalid
Requires-Python: >=3.9
Requires-Dist: langchain-llm7>=0.0.0
Requires-Dist: llmatch-messages>=0.0.0
Requires-Dist: langchain-core>=0.3.0
